README.md
setup.py
leslie/__init__.py
leslie/__main__.py
leslie/version.py
leslie.egg-info/PKG-INFO
leslie.egg-info/SOURCES.txt
leslie.egg-info/dependency_links.txt
leslie.egg-info/entry_points.txt
leslie.egg-info/requires.txt
leslie.egg-info/top_level.txt
leslie/commands/__init__.py
leslie/commands/predict.py
leslie/commands/subcommand.py
leslie/commands/test.py
leslie/commands/train.py
leslie/common/__init__.py
leslie/common/checks.py
leslie/common/file_utils.py
leslie/common/from_params.py
leslie/common/lazy.py
leslie/common/logging.py
leslie/common/params.py
leslie/common/registrable.py
leslie/common/tee.py
leslie/common/tqdm.py
leslie/common/util.py
leslie/data/__init__.py
leslie/data/batch.py
leslie/data/instance.py
leslie/data/vocabulary.py
leslie/data/dataset_readers/__init__.py
leslie/data/dataset_readers/dataset_reader.py
leslie/data/dataset_readers/text_classifier_dataset_reader.py
leslie/layers/__init__.py
leslie/models/__init__.py
leslie/models/archival.py
leslie/models/model.py
leslie/models/intent_slot/__init__.py
leslie/models/intent_slot/intent_slot_model.py
leslie/models/intent_slot/sf_id_intent_slot_model.py
leslie/models/text_classifier/__init__.py
leslie/models/text_classifier/aver_pooling_text_classifier_model.py
leslie/models/text_classifier/bert_text_classifier_model.py
leslie/models/text_classifier/cnn_test_classifier.py
leslie/models/text_classifier/text_classifier_model.py
leslie/modules/__init__.py
leslie/predictors/__init__.py
leslie/predictors/predictor.py
leslie/predictors/text_classifier_predictor.py